AUTHORS.txt
CHANGELOG.txt
LICENSE.txt
MANIFEST.in
README.md
setup.py
Flask_Images.egg-info/PKG-INFO
Flask_Images.egg-info/SOURCES.txt
Flask_Images.egg-info/dependency_links.txt
Flask_Images.egg-info/not-zip-safe
Flask_Images.egg-info/requires.txt
Flask_Images.egg-info/top_level.txt
flask_images/__init__.py
flask_images/core.py
flask_images/modes.py
flask_images/size.py