Metadata-Version: 1.1
Name: Flask-Images
Version: 2.1.0
Summary: Dynamic image resizing for Flask.
Home-page: http://github.com/mikeboers/Flask-Images
Author: Mike Boers
Author-email: flask_images@mikeboers.com
License: BSD-3
Platform: UNKNOWN
Classifier: Development Status :: 5 - Production/Stable
Classifier: Intended Audience :: Developers
Classifier: License :: OSI Approved :: BSD License
Classifier: Natural Language :: English
Classifier: Operating System :: OS Independent
Classifier: Programming Language :: Python :: 2
Classifier: Programming Language :: Python :: 3
Classifier: Topic :: Software Development :: Libraries :: Python Modules
